pathxio/__init__.py
pathxio/pathxio.py
pathxio-0.2.0.dist-info/METADATA
pathxio-0.2.0.dist-info/WHEEL
pathxio-0.2.0.dist-info/entry_points.txt
pathxio-0.2.0.dist-info/top_level.txt
pathxio-0.2.0.dist-info/RECORD
