Metadata-Version: 2.4
Name: pathxio
Version: 0.2.0
Summary: Safe, predictable filesystem operations for Python.
Author: holy
License-Expression: MIT
Project-URL: Documentation, https://github.com/holyholical/pathxio/blob/main/README.md
Project-URL: Repository, https://github.com/holyholical/pathxio.git
Project-URL: Bug Tracker, https://github.com/holyholical/pathxio/issues
Project-URL: Changelog, https://github.com/holyholical/pathxio/blob/main/CHANGELOG.md
Keywords: filesystem,file,path,safe,undo,copy,move,remove,async,cli
Classifier: Development Status :: 5 - Production/Stable
Classifier: Intended Audience :: Developers
Classifier: Topic :: Software Development :: Libraries
Classifier: Programming Language :: Python :: 3
Classifier: Operating System :: OS Independent
Requires-Python: >=3.8
Requires-Dist: aiofiles
